{
  "siteUrl": "https://twelve-sided-leviathan.com",
  "siteTitle": "Twelve-Sided Leviathan",
  "siteTagline": "A place for games & other oddities",
  "siteDescription": "A blog about tabletop roleplaying game design, dungeon crawling, OSR principles, and exploration-based gameplay.",
  "metaKeywords": "TTRPG, dungeon design, OSR, D&D, game design, exploration, tabletop RPG, old school renaissance",
  "googleVerification": "",
  "nav": [
    { "url": "", "label": "Home" },
    { "url": "blog/", "label": "Blog" },
    { "url": "about/", "label": "About" },
    { "url": "contact/", "label": "Contact" }
  ],
  "footerNav": [
    { "url": "blog/", "label": "Blog" },
    { "url": "about/", "label": "About" },
    { "url": "contact/", "label": "Contact" }
  ],
  "socialLinks": [],
  "siteBackgroundImage": "",
  "sidebarWidgets": [
    {
      "title": "Featured Articles",
      "links": [
        { "label": "Exploration Mechanics in Classic D&D", "url": "exploration-mechanics-in-classic-dnd/" },
        { "label": "Dungeon Design: Obstacles", "url": "dungeon-design-obstacles-support-exploration/" }
      ]
    },
    {
      "title": "Soundbreakers RPG",
      "image": "images/whale-skyline-public-domain.jpg",
      "imageAlt": "A whale breaching at sunset over a harbour skyline",
      "text": "Twelve-Sided Leviathan is a blog about old-school dungeon design and tabletop roleplaying.",
      "paragraphs": [
        "Written by a lifelong fan of OSR exploration, trap design, and wilderness travel."
      ],
      "links": [
        { "label": "Read more", "url": "about/" }
      ]
    }
  ]
}
